spy_tool/__init__.py
spy_tool/chrome_extension.py
spy_tool/crawler.py
spy_tool/datetime.py
spy_tool/decorators/__init__.py
spy_tool/decorators/prevent_duplicate_execution.py
spy_tool/entities/__init__.py
spy_tool/entities/account.py
spy_tool/exceptions.py
spy_tool/file.py
spy_tool/image.py
spy_tool/logger.py
spy_tool/math.py
spy_tool/misc.py
spy_tool/mixins/__init__.py
spy_tool/mixins/cp_mixin.py
spy_tool/notifier.py
spy_tool/project.py
spy_tool/run/__init__.py
spy_tool/run/js.py
spy_tool/spider.py
spy_tool/url.py
spy_tool/verify/__init__.py
spy_tool/verify/bezier_curve.py
spy_tool/verify/double_image_slider.py
spy_tool/verify/trajectory.py
spy_tool-0.2.4.dist-info/METADATA
spy_tool-0.2.4.dist-info/WHEEL
spy_tool-0.2.4.dist-info/RECORD
