Metadata-Version: 2.1
Name: spy-tool
Version: 0.2.4
Summary: 
Author: mathewgeola
Author-email: mathewgeola@163.com
Requires-Python: >=3.10,<3.13
Classifier: Programming Language :: Python :: 3
Classifier: Programming Language :: Python :: 3.10
Classifier: Programming Language :: Python :: 3.11
Classifier: Programming Language :: Python :: 3.12
Requires-Dist: colorlog (>=6.8.2,<7.0.0)
Requires-Dist: ddddocr (>=1.5.5,<2.0.0)
Requires-Dist: drissionpage (>=4.0.5.6,<5.0.0.0)
Requires-Dist: dynaconf (>=3.2.6,<4.0.0)
Requires-Dist: furl (>=2.1.3,<3.0.0)
Requires-Dist: httpx (>=0.27.0,<0.28.0)
Requires-Dist: matplotlib (>=3.9.1,<4.0.0)
Requires-Dist: numpy (<2)
Requires-Dist: opencv-python (>=4.10.0.84,<5.0.0.0)
Requires-Dist: pillow (>=10.4.0,<11.0.0)
Requires-Dist: psutil (>=6.0.0,<7.0.0)
Requires-Dist: py-mini-racer (>=0.6.0,<0.7.0)
Requires-Dist: pyexecjs (>=1.5.1,<2.0.0)
Requires-Dist: pyzbar (>=0.1.9,<0.2.0)
Requires-Dist: tqdm (>=4.66.4,<5.0.0)
Requires-Dist: walrus (>=0.9.4,<0.10.0)
Requires-Dist: yagmail (>=0.15.293,<0.16.0)
